onebot/__init__.py
onebot/plugins/__init__.py
onebot/plugins/acl.py
onebot/plugins/antispam.py
onebot/plugins/botui.py
onebot/plugins/execute.py
onebot/plugins/lastfm.py
onebot/plugins/psa.py
onebot/plugins/trakt.py
onebot/plugins/urlinfo.py
onebot/plugins/users.py
onebot/plugins/whatcd.py
onebot-1.3.3.dist-info/AUTHORS.rst
onebot-1.3.3.dist-info/LICENSE
onebot-1.3.3.dist-info/METADATA
onebot-1.3.3.dist-info/WHEEL
onebot-1.3.3.dist-info/entry_points.txt
onebot-1.3.3.dist-info/top_level.txt
onebot-1.3.3.dist-info/zip-safe
onebot-1.3.3.dist-info/RECORD
