Metadata-Version: 2.1
Name: onebot
Version: 1.3.3
Summary: OneBot is an ircbot based on irc3
Home-page: https://github.com/thomwiggers/onebot
Author: Thom Wiggers
Author-email: thom@thomwiggers.nl
License: BSD
Keywords: onebot irc
Platform: UNKNOWN
Classifier: Development Status :: 3 - Alpha
Classifier: Intended Audience :: Developers
Classifier: License :: OSI Approved :: BSD License
Classifier: Natural Language :: English
Classifier: Programming Language :: Python :: 3
Classifier: Programming Language :: Python :: 3.5
Classifier: Programming Language :: Python :: 3.6
Classifier: Programming Language :: Python :: 3.7
Classifier: Programming Language :: Python :: Implementation :: CPython
Requires-Dist: irc3 (>=1.1.3)
Requires-Dist: wheel
Requires-Dist: lfmh
Requires-Dist: musicbrainzngs
Requires-Dist: beautifulsoup4
Requires-Dist: html5lib (!=0.99999999)
Requires-Dist: requests
